KGlobal/__init__.py
KGlobal/__main__.py
KGlobal/credentials.py
KGlobal/exchangelib.py
KGlobal/filehandler.py
KGlobal/logging.py
KGlobal/main.py
KGlobal/setup_gui.py
KGlobal/toolbox.py
KGlobal/util.py
KGlobal/data/__init__.py
KGlobal/data/config.py
KGlobal/data/create_key.py
KGlobal/data/cryptography.py
KGlobal/data/error.py
KGlobal/data/picklemixin.py
KGlobal/reader/__init__.py
KGlobal/reader/_csv.py
KGlobal/reader/_excel.py
KGlobal/reader/_json.py
KGlobal/reader/_open.py
KGlobal/reader/_xml.py
KGlobal/sql/__init__.py
KGlobal/sql/config.py
KGlobal/sql/cursor.py
KGlobal/sql/engine.py
KGlobal/sql/queue.py
KGlobal-1.6.7.6.dist-info/LICENSE
KGlobal-1.6.7.6.dist-info/METADATA
KGlobal-1.6.7.6.dist-info/WHEEL
KGlobal-1.6.7.6.dist-info/entry_points.txt
KGlobal-1.6.7.6.dist-info/top_level.txt
KGlobal-1.6.7.6.dist-info/RECORD
